README.md
setup.py
py_calculator_new.egg-info/PKG-INFO
py_calculator_new.egg-info/SOURCES.txt
py_calculator_new.egg-info/dependency_links.txt
py_calculator_new.egg-info/entry_points.txt
py_calculator_new.egg-info/top_level.txt
src/__init__.py
src/calculator.py