Metadata-Version: 2.1
Name: py-calculator-new
Version: 0.0.1
Summary: An application that peforme simple calculaltion like calculator
Home-page: UNKNOWN
Author: Vinayak Gaikar
Author-email: vinayakgaikar1998@gmail.co,
License: UNKNOWN
Platform: UNKNOWN
Classifier: Programming Language :: Python :: 3
Classifier: License :: OSI Approved :: MIT License
Classifier: Operating System :: OS Independent
